nrelpy/__init__.py
nrelpy/atb.py
nrelpy/re_potential.py
nrelpy/version.py
nrelpy/data/ATBe_2022.pkl
nrelpy/utils/__init__.py
nrelpy/utils/data_io.py
nrelpy/utils/user_data.py
nrelpy-0.3.2.dist-info/LICENSE
nrelpy-0.3.2.dist-info/METADATA
nrelpy-0.3.2.dist-info/WHEEL
nrelpy-0.3.2.dist-info/top_level.txt
nrelpy-0.3.2.dist-info/RECORD
